iesopt/__init__.py
iesopt_py-1.0.0a1.dist-info/LICENSE
iesopt_py-1.0.0a1.dist-info/METADATA
iesopt_py-1.0.0a1.dist-info/WHEEL
iesopt_py-1.0.0a1.dist-info/RECORD
