Metadata-Version: 2.1
Name: iesopt-py
Version: 1.0.0a1
Summary: Low-overhead Python interface to the IESopt framework.
Home-page: https://github.com/ait-energy/IESopt.jl
License: MIT
Keywords: integrated energy systems,optimization,energy model,modelling
Author: Stefan Strömer
Author-email: 8915976+sstroemer@users.noreply.github.com
Maintainer: Stefan Strömer
Maintainer-email: 8915976+sstroemer@users.noreply.github.com
Requires-Python: >=3.10,<4.0
Classifier: Development Status :: 4 - Beta
Classifier: Intended Audience :: Science/Research
Classifier: License :: OSI Approved :: MIT License
Classifier: Programming Language :: Python :: 3
Classifier: Programming Language :: Python :: 3.10
Classifier: Programming Language :: Python :: 3.11
Classifier: Programming Language :: Python :: 3.12
Project-URL: Changelog, https://github.com/ait-energy/iesopt-py/blob/main/CHANGELOG.md
Project-URL: Documentation, https://ait-energy.github.io/IESopt.jl
Project-URL: Issues, https://github.com/ait-energy/iesopt-py/issues
Project-URL: Repository, https://github.com/ait-energy/iesopt-py
